Arzbot/__init__.py
schbot/__init__.py
Arzbot-0.1.0.dist-info/METADATA
Arzbot-0.1.0.dist-info/WHEEL
Arzbot-0.1.0.dist-info/top_level.txt
Arzbot-0.1.0.dist-info/RECORD
